unicodetext/__init__.py
unicodetext/unicode_blocks.py
unicodetext/unicode_categories.py
unicodetext-1.3.dist-info/LICENSE.txt
unicodetext-1.3.dist-info/METADATA
unicodetext-1.3.dist-info/WHEEL
unicodetext-1.3.dist-info/top_level.txt
unicodetext-1.3.dist-info/RECORD
