Metadata-Version: 2.1
Name: unicodetext
Version: 1.3
Summary: Processing unicode text.
Home-page: https://github.com/huang22/unicodetext
Author: huang22
Author-email: 1048507371@qq.com
License: MIT
Platform: UNKNOWN
Classifier: License :: OSI Approved :: MIT License
Classifier: Programming Language :: Python
Classifier: Programming Language :: Python :: Implementation :: CPython
Classifier: Programming Language :: Python :: Implementation :: PyPy
License-File: LICENSE.txt
